ragstack/__init__.py
ragstack_ai-1.1.0.dist-info/LICENSE.md
ragstack_ai-1.1.0.dist-info/METADATA
ragstack_ai-1.1.0.dist-info/WHEEL
ragstack_ai-1.1.0.dist-info/RECORD
