Metadata-Version: 2.1
Name: ragstack-ai
Version: 1.1.0
Summary: DataStax RAGStack
Home-page: https://github.com/datastax/ragstack-ai
License: BUSL-1.1
Author: DataStax
Requires-Python: >=3.9,<3.13
Classifier: License :: Other/Proprietary License
Classifier: Programming Language :: Python :: 3
Classifier: Programming Language :: Python :: 3.9
Classifier: Programming Language :: Python :: 3.10
Classifier: Programming Language :: Python :: 3.11
Classifier: Programming Language :: Python :: 3.12
Requires-Dist: ragstack-ai-colbert (==1.0.6)
Requires-Dist: ragstack-ai-langchain[colbert,google,nvidia] (==1.4.0)
Requires-Dist: ragstack-ai-llamaindex[azure,bedrock,colbert,google] (==1.0.8)
Project-URL: Documentation, https://docs.datastax.com/en/ragstack
Project-URL: Repository, https://github.com/datastax/ragstack-ai
